setup.py
model_converter/__init__.py
model_converter/main.py
model_converter.egg-info/PKG-INFO
model_converter.egg-info/SOURCES.txt
model_converter.egg-info/dependency_links.txt
model_converter.egg-info/entry_points.txt
model_converter.egg-info/not-zip-safe
model_converter.egg-info/top_level.txt