Metadata-Version: 1.0
Name: model-converter
Version: 0.0.5
Summary: Convert Pydantic Model to Dart Class
Home-page: https://github.com/ipconfiger
Author: Alexander.Li
Author-email: superpowerlee@gmail.com
License: MIT
Platform: UNKNOWN
